{
	"mod": "empty",
	"keys": {
		"spell": 88,
		"special": 67,
		"up": 38,
		"down": 40,
		"left": 37,
		"right": 39,
		"slow": 16,
		"shoot": 90
	},
	"keys2": {
		"spell": 68,
		"special": 70,
		"up": 101,
		"down": 98,
		"left": 97,
		"right": 99,
		"slow": 65,
		"shoot": 83
	},
	"locale": "zh_cn",
	"timezone": 8,
	"username": "User",
	"keysys": {
		"retry": 82,
		"menu_left": 37,
		"menu_down": 40,
		"menu_up": 38,
		"menu_right": 39,
		"menu_confirm": 90,
		"repfast": 17,
		"repslow": 16,
		"menu": 27,
		"snapshot": 36
	},
	"windowed": true,
	"resx": 1600,
	"resy": 900,
	"vsync": false,
	"sevolume": 100,
	"bgmvolume": 100
}